{"runtime":"node-legacy","schema_version":1,"generated_at":"2025-08-27T21:18:42.537Z","snippets":[{"id":"autoscaling-profiles-limits","title":"Autoscaling Profile Limits","description":"Monitor and manage autoscaling profile limits and usage","language":"javascript","tags":["autoscaling","profile","limits","monitoring","management"],"filename":"autoscaling-profiles-limits.js","file_path":"node-legacy/autoscaling-profiles-limits.js"},{"id":"avg-min-max","title":"Average, Minimum and Maximum","description":"Calculate minimum, maximum, and average values from device data","language":"javascript","tags":["data","calculation","average","min","max","statistics"],"filename":"avg-min-max.js","file_path":"node-legacy/avg-min-max.js"},{"id":"aws-iot-device-location","title":"AWS IoT Device Location","description":"AWS IoT Core Device Location service integration","language":"javascript","tags":["aws","iot","location","integration","tracking"],"filename":"aws-iot-device-location.js","file_path":"node-legacy/aws-iot-device-location.js"},{"id":"configuration-parameters-for-dynamic-last-value","title":"Dynamic Last Value Configuration","description":"Configuration parameters for dynamic last value displays","language":"javascript","tags":["configuration","dynamic","last-value","parameters","display"],"filename":"configuration-parameters-for-dynamic-last-value.js","file_path":"node-legacy/configuration-parameters-for-dynamic-last-value.js"},{"id":"console","title":"Console Hello World","description":"Hello World example with console output","language":"javascript","tags":["basic","console","hello-world"],"filename":"console.js","file_path":"node-legacy/console.js"},{"id":"create-device","title":"Create Device from Dashboard","description":"Create new devices dynamically using dashboard interface","language":"javascript","tags":["device","create","dashboard","dynamic","management"],"filename":"create-device.js","file_path":"node-legacy/create-device.js"},{"id":"data-amount","title":"Device Data Amount Report","description":"Get top 20 devices with highest data amount usage","language":"javascript","tags":["data","amount","report","usage","analytics"],"filename":"data-amount.js","file_path":"node-legacy/data-amount.js"},{"id":"data-retention","title":"Data Retention Management","description":"Implement custom data retention policies for device data","language":"javascript","tags":["data","retention","cleanup","management","storage"],"filename":"data-retention.js","file_path":"node-legacy/data-retention.js"},{"id":"data-transaction","title":"Data Transaction Summary","description":"Get total transaction count and statistics by user","language":"javascript","tags":["data","transaction","user","statistics","billing"],"filename":"data-transaction.js","file_path":"node-legacy/data-transaction.js"},{"id":"device-list","title":"Get Device List","description":"Retrieve and filter device list from your account","language":"javascript","tags":["devices","api","list","filtering"],"filename":"device-list.js","file_path":"node-legacy/device-list.js"},{"id":"device-offline","title":"Device Offline Alert","description":"Monitor devices and send alerts when they go offline","language":"javascript","tags":["device","offline","alert","monitoring","status"],"filename":"device-offline.js","file_path":"node-legacy/device-offline.js"},{"id":"downlink-dashboard","title":"Downlink from Dashboard","description":"Send downlink messages to devices triggered from dashboard","language":"javascript","tags":["downlink","dashboard","device","communication","control"],"filename":"downlink-dashboard.js","file_path":"node-legacy/downlink-dashboard.js"},{"id":"dynamic-notification","title":"Dynamic Notifications","description":"Send dynamic email, SMS and push notifications based on conditions","language":"javascript","tags":["notification","dynamic","email","sms","push","conditional"],"filename":"dynamic-notification.js","file_path":"node-legacy/dynamic-notification.js"},{"id":"email-export","title":"Email Export","description":"Export device data and send via email attachment","language":"javascript","tags":["email","export","data","attachment","csv"],"filename":"email-export.js","file_path":"node-legacy/email-export.js"},{"id":"find","title":"Find and Operate Data","description":"Find and operate data from devices using filtering and manipulation","language":"javascript","tags":["data","find","filter","operation","device"],"filename":"find.js","file_path":"node-legacy/find.js"},{"id":"generate-pdf-report","title":"Generate PDF Report","description":"Generate PDF report and send via email","language":"javascript","tags":["pdf","report","email","advanced"],"filename":"generate-pdf-report.js","file_path":"node-legacy/generate-pdf-report.js"},{"id":"geofence","title":"Geofence Trigger Alert","description":"Monitor device location and trigger alerts when entering/leaving geofenced areas","language":"javascript","tags":["geofence","location","alert","trigger"],"filename":"geofence.js","file_path":"node-legacy/geofence.js"},{"id":"http-get","title":"HTTP GET Request","description":"Make HTTP GET requests to external APIs and routes","language":"javascript","tags":["http","get","api","request","external"],"filename":"http-get.js","file_path":"node-legacy/http-get.js"},{"id":"mqtt-push","title":"MQTT Push from Dashboard","description":"Send MQTT messages triggered from dashboard interactions","language":"javascript","tags":["mqtt","push","dashboard","messaging","iot"],"filename":"mqtt-push.js","file_path":"node-legacy/mqtt-push.js"},{"id":"notifications","title":"Send Notifications","description":"Send notification to account and dashboard with optional dashboard linking","language":"javascript","tags":["notification","alert","dashboard","email"],"filename":"notifications.js","file_path":"node-legacy/notifications.js"}]}